Workbook

Sheet Dashboard
A2: SALES PERFORMANCE DASHBOARD — FY 2024
A3: Annual overview | All regions | All products
A7: TOTAL REVENUE | E7: TOTAL PROFIT | I7: AVG PROFIT MARGIN | M7: TOTAL LEADS | Q7: DEALS CLOSED
A8: =SUM('Monthly Summary'!B3:B14) -> 2189091.5 | E8: =SUM('Monthly Summary'!D3:D14) -> 983874.81 | I8: =AVERAGE('Monthly Summary'!E3:E14) -> 0.44932831 | M8: =SUM('Monthly Summary'!F3:F14) -> 5386 | Q8: =SUM('Monthly Summary'!G3:G14) -> 1147
A12: MONTHLY TRENDS
A33: REGIONAL & PRODUCT BREAKDOWN

Sheet Raw Data
A1: Month | B1: Quarter | C1: Region | D1: Sales Rep | E1: Product | F1: Units Sold | G1: Unit Price (£) | H1: Revenue (£) | I1: Cost (£) | J1: Profit (£) | K1: Profit Margin (%) | L1: Leads Generated | M1: Deals Closed | N1: Conversion Rate (%)
A2: Jan | B2: Q1 | C2: North | D2: Ben Carter | E2: Consulting | F2: 9 | G2: 2292.41 | H2: 20631.67 | I2: 12323.18 | J2: 8308.49 | K2: 0.40270576 | L2: 58 | M2: 10 | N2: 0.17241379
A3: Jan | B3: Q1 | C3: North | D3: Alice Johnson | E3: CRM Software | F3: 20 | G3: 1171.89 | H3: 23437.84 | I3: 10686.7 | J3: 12751.13 | K3: 0.54404056 | L3: 28 | M3: 9 | N3: 0.32142857
A4: Jan | B4: Q1 | C4: North | D4: Faisal Khan | E4: Analytics Suite | F4: 2 | G4: 1833.07 | H4: 3666.14 | I4: 2174.77 | J4: 1491.37 | K4: 0.40679608 | L4: 59 | M4: 5 | N4: 0.084745763
A5: Jan | B5: Q1 | C5: South | D5: David Lee | E5: Consulting | F5: 2 | G5: 2694.11 | H5: 5388.21 | I5: 2596.75 | J5: 2791.46 | K5: 0.51806814 | L5: 42 | M5: 4 | N5: 0.095238095
A6: Jan | B6: Q1 | C6: South | D6: Henry Moss | E6: Consulting | F6: 6 | G6: 2286.49 | H6: 13718.91 | I6: 8268.37 | J6: 5450.54 | K6: 0.39730117 | L6: 21 | M6: 3 | N6: 0.14285714
A7: Jan | B7: Q1 | C7: South | D7: Emma Brown | E7: Support Plan | F7: 5 | G7: 383.08 | H7: 1915.39 | I7: 993.69 | J7: 921.7 | K7: 0.48120886 | L7: 31 | M7: 8 | N7: 0.25806452
A8: Jan | B8: Q1 | C8: East | D8: Alice Johnson | E8: Analytics Suite | F8: 5 | G8: 2055.48 | H8: 10277.41 | I8: 5402.91 | J8: 4874.51 | K8: 0.47429312 | L8: 50 | M8: 4 | N8: 0.08
A9: Jan | B9: Q1 | C9: East | D9: Faisal Khan | E9: Analytics Suite | F9: 13 | G9: 1841.77 | H9: 23943.01 | I9: 14148.27 | J9: 9794.74 | K9: 0.40908563 | L9: 17 | M9: 12 | N9: 0.70588235
A10: Jan | B10: Q1 | C10: East | D10: David Lee | E10: Training Package | F10: 11 | G10: 973.73 | H10: 10711.05 | I10: 6652.24 | J10: 4058.81 | K10: 0.37893646 | L10: 21 | M10: 8 | N10: 0.38095238
A11: Jan | B11: Q1 | C11: West | D11: Emma Brown | E11: Consulting | F11: 7 | G11: 2402.64 | H11: 16818.45 | I11: 8273.02 | J11: 8545.43 | K11: 0.50809859 | L11: 32 | M11: 3 | N11: 0.09375
A12: Jan | B12: Q1 | C12: West | D12: David Lee | E12: Analytics Suite | F12: 7 | G12: 1818.44 | H12: 12729.05 | I12: 6351.31 | J12: 6377.73 | K12: 0.50103781 | L12: 44 | M12: 8 | N12: 0.18181818
A13: Jan | B13: Q1 | C13: West | D13: Faisal Khan | E13: Consulting | F13: 19 | G13: 2289.71 | H13: 43504.52 | I13: 22398.58 | J13: 21105.93 | K13: 0.48514345 | L13: 18 | M13: 9 | N13: 0.5
... A145: Dec | B145: Q4 | C145: West | D145: Ben Carter | E145: CRM Software | F145: 17 | G145: 1301.35 | H145: 22122.93 | I145: 11127.94 | J145: 10995 | K145: 0.49699544 | L145: 54 | M145: 14 | N145: 0.25925926

Sheet Monthly Summary
A1: Monthly Sales Performance Summary
A2: Month | B2: Total Revenue (£) | C2: Total Cost (£) | D2: Total Profit (£) | E2: Avg Profit Margin (%) | F2: Total Leads | G2: Total Deals Closed | H2: Avg Conversion Rate (%)
A3: Jan | B3: =SUMIF('Raw Data'!A:A,A3,'Raw Data'!H:H) -> 186741.65 | C3: =SUMIF('Raw Data'!A:A,A3,'Raw Data'!I:I) -> 100269.79 | D3: =SUMIF('Raw Data'!A:A,A3,'Raw Data'!J:J) -> 86471.84 | E3: =AVERAGEIF('Raw Data'!A:A,A3,'Raw Data'!K:K) -> 0.45889297 | F3: =SUMIF('Raw Data'!A:A,A3,'Raw Data'!L:L) -> 421 | G3: =SUMIF('Raw Data'!A:A,A3,'Raw Data'!M:M) -> 83 | H3: =AVERAGEIF('Raw Data'!A:A,A3,'Raw Data'!N:N) -> 0.25142923
A4: Feb | B4: =SUMIF('Raw Data'!A:A,A4,'Raw Data'!H:H) -> 212285.8 | C4: =SUMIF('Raw Data'!A:A,A4,'Raw Data'!I:I) -> 119870.75 | D4: =SUMIF('Raw Data'!A:A,A4,'Raw Data'!J:J) -> 92415.08 | E4: =AVERAGEIF('Raw Data'!A:A,A4,'Raw Data'!K:K) -> 0.42685327 | F4: =SUMIF('Raw Data'!A:A,A4,'Raw Data'!L:L) -> 474 | G4: =SUMIF('Raw Data'!A:A,A4,'Raw Data'!M:M) -> 112 | H4: =AVERAGEIF('Raw Data'!A:A,A4,'Raw Data'!N:N) -> 0.29356985
A5: Mar | B5: =SUMIF('Raw Data'!A:A,A5,'Raw Data'!H:H) -> 162259.27 | C5: =SUMIF('Raw Data'!A:A,A5,'Raw Data'!I:I) -> 92775.75 | D5: =SUMIF('Raw Data'!A:A,A5,'Raw Data'!J:J) -> 69483.53 | E5: =AVERAGEIF('Raw Data'!A:A,A5,'Raw Data'!K:K) -> 0.4435212 | F5: =SUMIF('Raw Data'!A:A,A5,'Raw Data'!L:L) -> 454 | G5: =SUMIF('Raw Data'!A:A,A5,'Raw Data'!M:M) -> 69 | H5: =AVERAGEIF('Raw Data'!A:A,A5,'Raw Data'!N:N) -> 0.15839846
A6: Apr | B6: =SUMIF('Raw Data'!A:A,A6,'Raw Data'!H:H) -> 191007.05 | C6: =SUMIF('Raw Data'!A:A,A6,'Raw Data'!I:I) -> 104618.96 | D6: =SUMIF('Raw Data'!A:A,A6,'Raw Data'!J:J) -> 86388.07 | E6: =AVERAGEIF('Raw Data'!A:A,A6,'Raw Data'!K:K) -> 0.45249897 | F6: =SUMIF('Raw Data'!A:A,A6,'Raw Data'!L:L) -> 421 | G6: =SUMIF('Raw Data'!A:A,A6,'Raw Data'!M:M) -> 108 | H6: =AVERAGEIF('Raw Data'!A:A,A6,'Raw Data'!N:N) -> 0.29981341
A7: May | B7: =SUMIF('Raw Data'!A:A,A7,'Raw Data'!H:H) -> 108546.66 | C7: =SUMIF('Raw Data'!A:A,A7,'Raw Data'!I:I) -> 62846.43 | D7: =SUMIF('Raw Data'!A:A,A7,'Raw Data'!J:J) -> 45700.25 | E7: =AVERAGEIF('Raw Data'!A:A,A7,'Raw Data'!K:K) -> 0.42943766 | F7: =SUMIF('Raw Data'!A:A,A7,'Raw Data'!L:L) -> 348 | G7: =SUMIF('Raw Data'!A:A,A7,'Raw Data'!M:M) -> 94 | H7: =AVERAGEIF('Raw Data'!A:A,A7,'Raw Data'!N:N) -> 0.30165868
A8: Jun | B8: =SUMIF('Raw Data'!A:A,A8,'Raw Data'!H:H) -> 169090.28 | C8: =SUMIF('Raw Data'!A:A,A8,'Raw Data'!I:I) -> 92833.04 | D8: =SUMIF('Raw Data'!A:A,A8,'Raw Data'!J:J) -> 76257.21 | E8: =AVERAGEIF('Raw Data'!A:A,A8,'Raw Data'!K:K) -> 0.45396588 | F8: =SUMIF('Raw Data'!A:A,A8,'Raw Data'!L:L) -> 418 | G8: =SUMIF('Raw Data'!A:A,A8,'Raw Data'!M:M) -> 100 | H8: =AVERAGEIF('Raw Data'!A:A,A8,'Raw Data'!N:N) -> 0.26643576
A9: Jul | B9: =SUMIF('Raw Data'!A:A,A9,'Raw Data'!H:H) -> 225761.08 | C9: =SUMIF('Raw Data'!A:A,A9,'Raw Data'!I:I) -> 125956.67 | D9: =SUMIF('Raw Data'!A:A,A9,'Raw Data'!J:J) -> 99804.4 | E9: =AVERAGEIF('Raw Data'!A:A,A9,'Raw Data'!K:K) -> 0.44522108 | F9: =SUMIF('Raw Data'!A:A,A9,'Raw Data'!L:L) -> 488 | G9: =SUMIF('Raw Data'!A:A,A9,'Raw Data'!M:M) -> 124 | H9: =AVERAGEIF('Raw Data'!A:A,A9,'Raw Data'!N:N) -> 0.27414946
A10: Aug | B10: =SUMIF('Raw Data'!A:A,A10,'Raw Data'!H:H) -> 133174.1 | C10: =SUMIF('Raw Data'!A:A,A10,'Raw Data'!I:I) -> 72254.86 | D10: =SUMIF('Raw Data'!A:A,A10,'Raw Data'!J:J) -> 60919.25 | E10: =AVERAGEIF('Raw Data'!A:A,A10,'Raw Data'!K:K) -> 0.4496491 | F10: =SUMIF('Raw Data'!A:A,A10,'Raw Data'!L:L) -> 429 | G10: =SUMIF('Raw Data'!A:A,A10,'Raw Data'!M:M) -> 79 | H10: =AVERAGEIF('Raw Data'!A:A,A10,'Raw Data'!N:N) -> 0.22153237
A11: Sep | B11: =SUMIF('Raw Data'!A:A,A11,'Raw Data'!H:H) -> 192962.85 | C11: =SUMIF('Raw Data'!A:A,A11,'Raw Data'!I:I) -> 106317.21 | D11: =SUMIF('Raw Data'!A:A,A11,'Raw Data'!J:J) -> 86645.65 | E11: =AVERAGEIF('Raw Data'!A:A,A11,'Raw Data'!K:K) -> 0.45889718 | F11: =SUMIF('Raw Data'!A:A,A11,'Raw Data'!L:L) -> 472 | G11: =SUMIF('Raw Data'!A:A,A11,'Raw Data'!M:M) -> 102 | H11: =AVERAGEIF('Raw Data'!A:A,A11,'Raw Data'!N:N) -> 0.22263282
A12: Oct | B12: =SUMIF('Raw Data'!A:A,A12,'Raw Data'!H:H) -> 237926.15 | C12: =SUMIF('Raw Data'!A:A,A12,'Raw Data'!I:I) -> 134215.18 | D12: =SUMIF('Raw Data'!A:A,A12,'Raw Data'!J:J) -> 103710.96 | E12: =AVERAGEIF('Raw Data'!A:A,A12,'Raw Data'!K:K) -> 0.45324704 | F12: =SUMIF('Raw Data'!A:A,A12,'Raw Data'!L:L) -> 485 | G12: =SUMIF('Raw Data'!A:A,A12,'Raw Data'!M:M) -> 60 | H12: =AVERAGEIF('Raw Data'!A:A,A12,'Raw Data'!N:N) -> 0.15522648
A13: Nov | B13: =SUMIF('Raw Data'!A:A,A13,'Raw Data'!H:H) -> 149779.73 | C13: =SUMIF('Raw Data'!A:A,A13,'Raw Data'!I:I) -> 79099.79 | D13: =SUMIF('Raw Data'!A:A,A13,'Raw Data'!J:J) -> 70679.93 | E13: =AVERAGEIF('Raw Data'!A:A,A13,'Raw Data'!K:K) -> 0.45323943 | F13: =SUMIF('Raw Data'!A:A,A13,'Raw Data'!L:L) -> 452 | G13: =SUMIF('Raw Data'!A:A,A13,'Raw Data'!M:M) -> 105 | H13: =AVERAGEIF('Raw Data'!A:A,A13,'Raw Data'!N:N) -> 0.27506244
A14: Dec | B14: =SUMIF('Raw Data'!A:A,A14,'Raw Data'!H:H) -> 219556.85 | C14: =SUMIF('Raw Data'!A:A,A14,'Raw Data'!I:I) -> 114158.21 | D14: =SUMIF('Raw Data'!A:A,A14,'Raw Data'!J:J) -> 105398.64 | E14: =AVERAGEIF('Raw Data'!A:A,A14,'Raw Data'!K:K) -> 0.46651589 | F14: =SUMIF('Raw Data'!A:A,A14,'Raw Data'!L:L) -> 524 | G14: =SUMIF('Raw Data'!A:A,A14,'Raw Data'!M:M) -> 111 | H14: =AVERAGEIF('Raw Data'!A:A,A14,'Raw Data'!N:N) -> 0.26719426
A15: TOTAL / AVG | B15: =SUM(B3:B14) -> 2189091.5 | C15: =SUM(C3:C14) -> 1205216.6 | D15: =SUM(D3:D14) -> 983874.81 | E15: =AVERAGE(E3:E14) -> 0.44932831 | F15: =SUM(F3:F14) -> 5386 | G15: =SUM(G3:G14) -> 1147 | H15: =AVERAGE(H3:H14) -> 0.24892527

Sheet Regional Summary
A1: Regional Sales Performance Summary
A2: Region | B2: Total Revenue (£) | C2: Total Profit (£) | D2: Avg Profit Margin (%) | E2: Total Leads | F2: Deals Closed | G2: Avg Conversion Rate (%)
A3: North | B3: =SUMIF('Raw Data'!C:C,A3,'Raw Data'!H:H) -> 513934.18 | C3: =SUMIF('Raw Data'!C:C,A3,'Raw Data'!J:J) -> 228855.29 | D3: =AVERAGEIF('Raw Data'!C:C,A3,'Raw Data'!K:K) -> 0.44390577 | E3: =SUMIF('Raw Data'!C:C,A3,'Raw Data'!L:L) -> 1447 | F3: =SUMIF('Raw Data'!C:C,A3,'Raw Data'!M:M) -> 310 | G3: =AVERAGEIF('Raw Data'!C:C,A3,'Raw Data'!N:N) -> 0.25993712
A4: South | B4: =SUMIF('Raw Data'!C:C,A4,'Raw Data'!H:H) -> 527833.46 | C4: =SUMIF('Raw Data'!C:C,A4,'Raw Data'!J:J) -> 237715.51 | D4: =AVERAGEIF('Raw Data'!C:C,A4,'Raw Data'!K:K) -> 0.45162597 | E4: =SUMIF('Raw Data'!C:C,A4,'Raw Data'!L:L) -> 1363 | F4: =SUMIF('Raw Data'!C:C,A4,'Raw Data'!M:M) -> 279 | G4: =AVERAGEIF('Raw Data'!C:C,A4,'Raw Data'!N:N) -> 0.22522958
A5: East | B5: =SUMIF('Raw Data'!C:C,A5,'Raw Data'!H:H) -> 570044.1 | C5: =SUMIF('Raw Data'!C:C,A5,'Raw Data'!J:J) -> 262042.03 | D5: =AVERAGEIF('Raw Data'!C:C,A5,'Raw Data'!K:K) -> 0.4505835 | E5: =SUMIF('Raw Data'!C:C,A5,'Raw Data'!L:L) -> 1280 | F5: =SUMIF('Raw Data'!C:C,A5,'Raw Data'!M:M) -> 308 | G5: =AVERAGEIF('Raw Data'!C:C,A5,'Raw Data'!N:N) -> 0.28745893
A6: West | B6: =SUMIF('Raw Data'!C:C,A6,'Raw Data'!H:H) -> 577279.73 | C6: =SUMIF('Raw Data'!C:C,A6,'Raw Data'!J:J) -> 255261.98 | D6: =AVERAGEIF('Raw Data'!C:C,A6,'Raw Data'!K:K) -> 0.45119798 | E6: =SUMIF('Raw Data'!C:C,A6,'Raw Data'!L:L) -> 1296 | F6: =SUMIF('Raw Data'!C:C,A6,'Raw Data'!M:M) -> 250 | G6: =AVERAGEIF('Raw Data'!C:C,A6,'Raw Data'!N:N) -> 0.22307543

Sheet Product Summary
A1: Product Performance Summary
A2: Product | B2: Units Sold | C2: Total Revenue (£) | D2: Total Profit (£) | E2: Avg Profit Margin (%) | F2: Avg Unit Price (£) | G2: Revenue Share (%)
A3: CRM Software | B3: =SUMIF('Raw Data'!E:E,A3,'Raw Data'!F:F) -> 322 | C3: =SUMIF('Raw Data'!E:E,A3,'Raw Data'!H:H) -> 388974.12 | D3: =SUMIF('Raw Data'!E:E,A3,'Raw Data'!J:J) -> 174056.04 | E3: =AVERAGEIF('Raw Data'!E:E,A3,'Raw Data'!K:K) -> 0.45265901 | F3: =AVERAGEIF('Raw Data'!E:E,A3,'Raw Data'!G:G) -> 1200.6961 | G3: =C3/SUM(C3:C7) -> 0.17768747
A4: Training Package | B4: =SUMIF('Raw Data'!E:E,A4,'Raw Data'!F:F) -> 231 | C4: =SUMIF('Raw Data'!E:E,A4,'Raw Data'!H:H) -> 196619.8 | D4: =SUMIF('Raw Data'!E:E,A4,'Raw Data'!J:J) -> 85687.85 | E4: =AVERAGEIF('Raw Data'!E:E,A4,'Raw Data'!K:K) -> 0.43855279 | F4: =AVERAGEIF('Raw Data'!E:E,A4,'Raw Data'!G:G) -> 846.9435 | G4: =C4/SUM(C3:C7) -> 0.089817992
A5: Consulting | B5: =SUMIF('Raw Data'!E:E,A5,'Raw Data'!F:F) -> 279 | C5: =SUMIF('Raw Data'!E:E,A5,'Raw Data'!H:H) -> 671262.73 | D5: =SUMIF('Raw Data'!E:E,A5,'Raw Data'!J:J) -> 307969.51 | E5: =AVERAGEIF('Raw Data'!E:E,A5,'Raw Data'!K:K) -> 0.46388716 | F5: =AVERAGEIF('Raw Data'!E:E,A5,'Raw Data'!G:G) -> 2453.0428 | G5: =C5/SUM(C3:C7) -> 0.30663987
A6: Support Plan | B6: =SUMIF('Raw Data'!E:E,A6,'Raw Data'!F:F) -> 386 | C6: =SUMIF('Raw Data'!E:E,A6,'Raw Data'!H:H) -> 156435.43 | D6: =SUMIF('Raw Data'!E:E,A6,'Raw Data'!J:J) -> 70228.09 | E6: =AVERAGEIF('Raw Data'!E:E,A6,'Raw Data'!K:K) -> 0.44708497 | F6: =AVERAGEIF('Raw Data'!E:E,A6,'Raw Data'!G:G) -> 401.85972 | G6: =C6/SUM(C3:C7) -> 0.071461349
A7: Analytics Suite | B7: =SUMIF('Raw Data'!E:E,A7,'Raw Data'!F:F) -> 428 | C7: =SUMIF('Raw Data'!E:E,A7,'Raw Data'!H:H) -> 775799.39 | D7: =SUMIF('Raw Data'!E:E,A7,'Raw Data'!J:J) -> 345933.32 | E7: =AVERAGEIF('Raw Data'!E:E,A7,'Raw Data'!K:K) -> 0.44398603 | F7: =AVERAGEIF('Raw Data'!E:E,A7,'Raw Data'!G:G) -> 1808.0328 | G7: =C7/SUM(C3:C7) -> 0.35439332
